.bzrignore
README.txt
setup.py
src/djpasty/__init__.py
src/djpasty.egg-info/PKG-INFO
src/djpasty.egg-info/SOURCES.txt
src/djpasty.egg-info/dependency_links.txt
src/djpasty.egg-info/not-zip-safe
src/djpasty.egg-info/requires.txt
src/djpasty.egg-info/top_level.txt
src/djpasty/management/__init__.py
src/djpasty/management/commands/__init__.py
src/djpasty/management/commands/pasteserver.py