Metadata-Version: 1.0
Name: djpasty
Version: 0.1
Summary: Djpasty makes it easy to run Django with the Paste webserver.
Home-page: https://launchpad.net/djpasty
Author: Jeroen Vloothuis
Author-email: jeroen.vloothuis@xs4all.nl
License: UNKNOWN
Platform: UNKNOWN
Classifier: Development Status :: 3 - Alpha
Classifier: Programming Language :: Python
Classifier: Intended Audience :: Developers
Classifier: License :: OSI Approved :: BSD License
Classifier: Framework :: Django
